mb_std/__init__.py
mb_std/concurrency.py
mb_std/date.py
mb_std/dict.py
mb_std/dotenv.py
mb_std/http.py
mb_std/json.py
mb_std/logging.py
mb_std/mongo.py
mb_std/net.py
mb_std/result.py
mb_std/shell.py
mb_std/str.py
mb_std/telegram.py
mb_std-0.4.7.dist-info/METADATA
mb_std-0.4.7.dist-info/WHEEL
mb_std-0.4.7.dist-info/top_level.txt
mb_std-0.4.7.dist-info/RECORD
