Metadata-Version: 2.1
Name: mb-std
Version: 0.4.7
Requires-Dist: requests (~=2.28.1)
Requires-Dist: PySocks (==1.7.1)
Requires-Dist: sorcery (==0.2.2)
Requires-Dist: pydash (==5.1.0)
Requires-Dist: wrapt (==1.14.1)
Requires-Dist: python-dateutil (==2.8.2)
Requires-Dist: pymongo (==4.1.1)
Requires-Dist: pydantic (~=1.9.0)
Requires-Dist: python-dotenv (==0.20.0)
Provides-Extra: dev
Requires-Dist: pytest (==7.1.2) ; extra == 'dev'
Requires-Dist: pre-commit (==2.19.0) ; extra == 'dev'
Requires-Dist: pytest-xdist (==2.5.0) ; extra == 'dev'
Requires-Dist: wheel (==0.37.1) ; extra == 'dev'
Requires-Dist: twine (==4.0.1) ; extra == 'dev'
Requires-Dist: pip-audit (==2.4.0) ; extra == 'dev'
